opentelemetry/exporter/jaeger/thrift/__init__.py
opentelemetry/exporter/jaeger/thrift/py.typed
opentelemetry/exporter/jaeger/thrift/send.py
opentelemetry/exporter/jaeger/thrift/version.py
opentelemetry/exporter/jaeger/thrift/gen/__init__.py
opentelemetry/exporter/jaeger/thrift/gen/agent/Agent-remote
opentelemetry/exporter/jaeger/thrift/gen/agent/Agent.py
opentelemetry/exporter/jaeger/thrift/gen/agent/__init__.py
opentelemetry/exporter/jaeger/thrift/gen/agent/constants.py
opentelemetry/exporter/jaeger/thrift/gen/agent/ttypes.py
opentelemetry/exporter/jaeger/thrift/gen/jaeger/Collector-remote
opentelemetry/exporter/jaeger/thrift/gen/jaeger/Collector.py
opentelemetry/exporter/jaeger/thrift/gen/jaeger/__init__.py
opentelemetry/exporter/jaeger/thrift/gen/jaeger/constants.py
opentelemetry/exporter/jaeger/thrift/gen/jaeger/ttypes.py
opentelemetry/exporter/jaeger/thrift/gen/zipkincore/ZipkinCollector-remote
opentelemetry/exporter/jaeger/thrift/gen/zipkincore/ZipkinCollector.py
opentelemetry/exporter/jaeger/thrift/gen/zipkincore/__init__.py
opentelemetry/exporter/jaeger/thrift/gen/zipkincore/constants.py
opentelemetry/exporter/jaeger/thrift/gen/zipkincore/ttypes.py
opentelemetry/exporter/jaeger/thrift/translate/__init__.py
opentelemetry_exporter_jaeger_thrift-1.19.0.dist-info/METADATA
opentelemetry_exporter_jaeger_thrift-1.19.0.dist-info/WHEEL
opentelemetry_exporter_jaeger_thrift-1.19.0.dist-info/entry_points.txt
opentelemetry_exporter_jaeger_thrift-1.19.0.dist-info/licenses/LICENSE
opentelemetry_exporter_jaeger_thrift-1.19.0.dist-info/RECORD
