Metadata-Version: 2.1
Name: opentelemetry-exporter-jaeger-thrift
Version: 1.19.0
Summary: Jaeger Thrift Exporter for OpenTelemetry
Project-URL: Homepage, https://github.com/open-telemetry/opentelemetry-python/tree/main/exporter/opentelemetry-exporter-jaeger-thrift
Author-email: OpenTelemetry Authors <cncf-opentelemetry-contributors@lists.cncf.io>
License-Expression: Apache-2.0
License-File: LICENSE
Classifier: Development Status :: 5 - Production/Stable
Classifier: Intended Audience :: Developers
Classifier: License :: OSI Approved :: Apache Software License
Classifier: Programming Language :: Python
Classifier: Programming Language :: Python :: 3
Classifier: Programming Language :: Python :: 3.7
Classifier: Programming Language :: Python :: 3.8
Classifier: Programming Language :: Python :: 3.9
Classifier: Programming Language :: Python :: 3.10
Classifier: Programming Language :: Python :: 3.11
Classifier: Typing :: Typed
Requires-Python: >=3.7
Requires-Dist: opentelemetry-api~=1.3
Requires-Dist: opentelemetry-sdk~=1.11
Requires-Dist: thrift>=0.10.0
Provides-Extra: test
